UltraEZLoadingBar/Core.py
UltraEZLoadingBar/__init__.py
ultraezloadingbar-0.0.0.7.dist-info/METADATA
ultraezloadingbar-0.0.0.7.dist-info/WHEEL
ultraezloadingbar-0.0.0.7.dist-info/top_level.txt
ultraezloadingbar-0.0.0.7.dist-info/RECORD
