Metadata-Version: 2.4
Name: UltraEZLoadingBar
Version: 0.0.0.7
Summary: A simple console-based loading bar for Python.
Author: ItsAlexander91
Author-email: alexander.bagwell9@gmail.com
Classifier: Programming Language :: Python :: 3
Classifier: License :: OSI Approved :: MIT License
Classifier: Operating System :: OS Independent
Requires-Python: >=3.6
Requires-Dist: cryptography
Dynamic: author
Dynamic: author-email
Dynamic: classifier
Dynamic: description
Dynamic: description-content-type
Dynamic: requires-dist
Dynamic: requires-python
Dynamic: summary
